cease/__init__.py
cease/config_builder/__init__.py
cease/config_builder/dataset_config.py
cease/data/__init__.py
cease/data/make_dataset.py
cease/features/__init__.py
cease/features/build_features.py
cease/models/__init__.py
cease/models/predict_model.py
cease/models/train_model.py
cease/visualization/__init__.py
cease/visualization/visualize.py
cease-0.1.0.dist-info/LICENSE
cease-0.1.0.dist-info/METADATA
cease-0.1.0.dist-info/WHEEL
cease-0.1.0.dist-info/top_level.txt
cease-0.1.0.dist-info/RECORD
