Metadata-Version: 2.1
Name: cease
Version: 0.1.0
Summary: Counterfactual Explanations for Accurate Surrogate model Extraction
Author: na
License: MIT
License-File: LICENSE
